lego_museum_structurizer/__init__.py
lego_museum_structurizer/main.py
lego_museum_structurizer/prompts.py
lego_museum_structurizer-2025.12.20202603.dist-info/METADATA
lego_museum_structurizer-2025.12.20202603.dist-info/WHEEL
lego_museum_structurizer-2025.12.20202603.dist-info/top_level.txt
lego_museum_structurizer-2025.12.20202603.dist-info/RECORD
