Metadata-Version: 2.4
Name: lego-museum-structurizer
Version: 2025.12.20202603
Summary: The package gives users a simple, text‑based interface for turning their free‑form imagination about a secret Lego museum into a machine‑friendly summary. A user writes a brief description of the scen
Author-email: lego-museum-structurizer <hi@eugene.plus>
License: MIT
Project-URL: Homepage, https://github.com/chigwell/lego-museum-structurizer
Requires-Python: >=3.9
Requires-Dist: langchain-llm7>=0.0.0
Requires-Dist: llmatch-messages>=0.0.0
Requires-Dist: langchain-core>=0.3.0
